{"cameraMode":{"drawMode":0,"name":"Shaded","section":"Shading Mode"},"sceneLighting":false,"audioPlay":false,"sceneViewState":{"m_AlwaysRefresh":false,"showFog":true,"showSkybox":false,"showFlares":true,"showImageEffects":true,"showParticleSystems":true,"showVisualEffectGraphs":true,"m_FxEnabled":true},"in2DMode":false,"pivot":{"x":-0.45691192150115969,"y":1.6202212572097779,"z":1.0170722007751465},"rotation":{"x":-0.050386544317007068,"y":-0.559610903263092,"z":0.034138113260269168,"w":-0.8265728950500488},"size":2.5308806896209719,"orthographic":false}